dagster_evidence/__init__.py
dagster_evidence/resource.py
dagster_evidence/lib/__init__.py
dagster_evidence/lib/evidence_project.py
dagster_evidence-0.1.7.dist-info/METADATA
dagster_evidence-0.1.7.dist-info/WHEEL
dagster_evidence-0.1.7.dist-info/entry_points.txt
dagster_evidence-0.1.7.dist-info/top_level.txt
dagster_evidence-0.1.7.dist-info/RECORD
