Metadata-Version: 2.4
Name: dagster-evidence
Version: 0.1.7
Summary: Dagster integration with evidence.dev
Requires-Python: >=3.10
Requires-Dist: dagster>=1.10.9
